youtube_dl_gui/__init__.py
youtube_dl_gui/__main__.py
youtube_dl_gui/app.py
youtube_dl_gui/darktheme.py
youtube_dl_gui/downloaders.py
youtube_dl_gui/downloadmanager.py
youtube_dl_gui/flagart.py
youtube_dl_gui/formats.py
youtube_dl_gui/info.py
youtube_dl_gui/logmanager.py
youtube_dl_gui/mainframe.py
youtube_dl_gui/optionsframe.py
youtube_dl_gui/optionsmanager.py
youtube_dl_gui/parsers.py
youtube_dl_gui/updatemanager.py
youtube_dl_gui/utils.py
youtube_dl_gui/version.py
youtube_dl_gui/widgets.py
youtube_dl_gui/data/pixmaps/arrow_down_32px.png
youtube_dl_gui/data/pixmaps/arrow_up_32px.png
youtube_dl_gui/data/pixmaps/camera_32px.png
youtube_dl_gui/data/pixmaps/cloud_download_32px.png
youtube_dl_gui/data/pixmaps/delete_32px.png
youtube_dl_gui/data/pixmaps/folder_32px.png
youtube_dl_gui/data/pixmaps/pause_32px.png
youtube_dl_gui/data/pixmaps/play_arrow_32px.png
youtube_dl_gui/data/pixmaps/reload_32px.png
youtube_dl_gui/data/pixmaps/settings_20px.png
youtube_dl_gui/data/pixmaps/stop_32px.png
youtube_dl_gui/data/pixmaps/youtube-dl-gui.png
youtube_dl_gui/locale/ar_SA/LC_MESSAGES/youtube_dl_gui.mo
youtube_dl_gui/locale/cs_CZ/LC_MESSAGES/youtube_dl_gui.mo
youtube_dl_gui/locale/de_DE/LC_MESSAGES/youtube_dl_gui.mo
youtube_dl_gui/locale/en_US/LC_MESSAGES/youtube_dl_gui.mo
youtube_dl_gui/locale/es_CU/LC_MESSAGES/youtube_dl_gui.mo
youtube_dl_gui/locale/es_ES/LC_MESSAGES/youtube_dl_gui.mo
youtube_dl_gui/locale/fr_FR/LC_MESSAGES/youtube_dl_gui.mo
youtube_dl_gui/locale/it_IT/LC_MESSAGES/youtube_dl_gui.mo
youtube_dl_gui/locale/ja_JP/LC_MESSAGES/youtube_dl_gui.mo
youtube_dl_gui/locale/ko_KR/LC_MESSAGES/youtube_dl_gui.mo
youtube_dl_gui/locale/pl_PL/LC_MESSAGES/youtube_dl_gui.mo
youtube_dl_gui/locale/pt_BR/LC_MESSAGES/youtube_dl_gui.mo
youtube_dl_gui/locale/ru_RU/LC_MESSAGES/youtube_dl_gui.mo
youtube_dl_gui/locale/sk_SK/LC_MESSAGES/youtube_dl_gui.mo
youtube_dl_gui/locale/sq_AL/LC_MESSAGES/youtube_dl_gui.mo
youtube_dl_gui/locale/zh_CN/LC_MESSAGES/youtube_dl_gui.mo
yt_dlg-1.8.5.dist-info/AUTHORS
yt_dlg-1.8.5.dist-info/LICENSE
yt_dlg-1.8.5.dist-info/METADATA
yt_dlg-1.8.5.dist-info/WHEEL
yt_dlg-1.8.5.dist-info/entry_points.txt
yt_dlg-1.8.5.dist-info/top_level.txt
yt_dlg-1.8.5.dist-info/RECORD
