Metadata-Version: 2.1
Name: yt-dlg
Version: 1.8.5
Summary: Youtube Downloader GUI
Home-page: https://oleksis.github.io/youtube-dl-gui/
Download-URL: https://github.com/oleksis/youtube-dl-gui/releases/latest
Author: Sotiris Papadopoulos
Author-email: ytubedlg@gmail.com
Maintainer: Oleksis Fraga
Maintainer-email: oleksis.fraga@gmail.com
License: UNLICENSE
Project-URL: Source, https://github.com/oleksis/youtube-dl-gui/
Project-URL: Tracker, https://github.com/oleksis/youtube-dl-gui/issues
Project-URL: Funding, https://oleksis.github.io/youtube-dl-gui/donate.html
Classifier: Topic :: Multimedia :: Video
Classifier: Development Status :: 5 - Production/Stable
Classifier: Environment :: MacOS X :: Cocoa
Classifier: Environment :: Win32 (MS Windows)
Classifier: Environment :: X11 Applications :: GTK
Classifier: License :: Public Domain
Classifier: Programming Language :: Python :: 3
Classifier: Programming Language :: Python :: 3 :: Only
Classifier: Programming Language :: Python :: 3.7
Classifier: Programming Language :: Python :: 3.8
Classifier: Programming Language :: Python :: 3.9
Classifier: Programming Language :: Python :: 3.10
Classifier: Programming Language :: Python :: 3.11
Classifier: Programming Language :: Python :: Implementation :: CPython
Requires-Python: >=3.7
License-File: LICENSE
License-File: AUTHORS
Requires-Dist: pypubsub (>=4.0.3)
Requires-Dist: wxPython (<=4.2.1a1,>=4.0.7.post2)
Provides-Extra: binaries
Requires-Dist: polib (>=1.1.0) ; extra == 'binaries'
Requires-Dist: pyinstaller (<=5.8.0,>=3.6) ; extra == 'binaries'
